Workbook
Name aporte_mensal: Simulador!$E$26
Name Patrimõnio: Simulador!$E$29
Name Qtd_anos: Simulador!$E$27
Name rendimento_carteira: Simulador!$E$22
Name Taxa_mensal: Simulador!$E$28

Sheet Simulador
C2: DRE INVEST
C17: O simulador da DRE INVEST poderá te auxiliar, projetando cenários futuros conforme o seu perfil de investidor
C18: Orientações: Preencha os campos com fundo branco e planeje seu futuro
C20: CONFIGURAÇÕES
C21: Salário | E21: 4200
C22: Rendimento de Carteira | E22: 0.008
C23: Sugestão de Investimento (30%) | E23: =E21*30% -> 1260
C25: INVESTIMENTO MENSAL | E25: SIMULADORES
C26: Quanto Investir por mês ? | E26: 1260
C27: Por quantos anos? | E27: 5
C28: Taxa de Rendimento mensal? | E28: 0.01079
C29: Patrimônio Acumulado? | E29: =FV(Taxa_mensal,Qtd_anos*12,aporte_mensal*-1) -> 105558.91
C30: Dividendos mensais ? | E30: =Patrimõnio*rendimento_carteira -> 844.47129
C32: CENÁRIOS | D32: SIMULADORES | E32: DIVIDENDOS
A33: 2 | C33: Quanto em 2 anos? | D33: =FV($E$28,A33*12,-$E$26) -> 34306.81 | E33: =D33*rendimento_carteira -> 274.45448
A34: 5 | C34: Quanto em 5 anos? | D34: =FV($E$28,A34*12,-$E$26) -> 105558.91 | E34: =D34*rendimento_carteira -> 844.47129
A35: 10 | C35: Quanto em 10 anos? | D35: =FV($E$28,A35*12,-$E$26) -> 306538.11 | E35: =D35*rendimento_carteira -> 2452.3049
A36: 20 | C36: Quanto em 20anos? | D36: =FV($E$28,A36*12,-$E$26) -> 1417750 | E36: =D36*rendimento_carteira -> 11342
A37: 30 | C37: Quanto em 30 anos? | D37: =FV($E$28,A37*12,-$E$26) -> 5445933.8 | E37: =D37*rendimento_carteira -> 43567.47
C39: PERFIL | E39: AGRESSIVO
C40: Valor a ser investido por mês | E40: =aporte_mensal -> 1260
C41: TIPO DE FII | D41: PERCENTUAL SUGERIDO | E41: VALORES
C42: PAPEL | D42: =VLOOKUP($E$39&"-"&C42,'% FII'!$B$2:$E$19,4,FALSE) -> 0.5 | E42: =D42*$E$40 -> 630
C43: TIJOLOS | D43: =VLOOKUP($E$39&"-"&C43,'% FII'!$B$2:$E$19,4,FALSE) -> 0.1 | E43: =D43*$E$40 -> 126
C44: HÍBRIDOS | D44: =VLOOKUP($E$39&"-"&C44,'% FII'!$B$2:$E$19,4,FALSE) -> 0.05 | E44: =D44*$E$40 -> 63
C45: FOFS | D45: =VLOOKUP($E$39&"-"&C45,'% FII'!$B$2:$E$19,4,FALSE) -> 0.05 | E45: =D45*$E$40 -> 63
C46: DESENVOLVIMENTO | D46: =VLOOKUP($E$39&"-"&C46,'% FII'!$B$2:$E$19,4,FALSE) -> 0.2 | E46: =D46*$E$40 -> 252
C47: HOTELARIAS | D47: =VLOOKUP($E$39&"-"&C47,'% FII'!$B$2:$E$19,4,FALSE) -> 0.1 | E47: =D47*$E$40 -> 126
E48: =SUM(E42:E47) -> 1260

Sheet % FII
B1: CHAVE | C1: Perfil | D1: TIPO DE FII | E1: %
B2: =C2&"-"&D2 -> CONSERVADOR-PAPEL | C2: CONSERVADOR | D2: PAPEL | E2: 0.25
B3: =C3&"-"&D3 -> CONSERVADOR-TIJOLOS | C3: CONSERVADOR | D3: TIJOLOS | E3: 0.55
B4: =C4&"-"&D4 -> CONSERVADOR-HÍBRIDOS | C4: CONSERVADOR | D4: HÍBRIDOS | E4: 0.1
B5: =C5&"-"&D5 -> CONSERVADOR-FOFS | C5: CONSERVADOR | D5: FOFS | E5: 0.1
B6: =C6&"-"&D6 -> CONSERVADOR-DESENVOLVIMENTO | C6: CONSERVADOR | D6: DESENVOLVIMENTO | E6: 0
B7: =C7&"-"&D7 -> CONSERVADOR-HOTELARIAS | C7: CONSERVADOR | D7: HOTELARIAS | E7: 0
B8: =C8&"-"&D8 -> MODERADO-PAPEL | C8: MODERADO | D8: PAPEL | E8: 0.3
B9: =C9&"-"&D9 -> MODERADO-TIJOLOS | C9: MODERADO | D9: TIJOLOS | E9: 0.42
B10: =C10&"-"&D10 -> MODERADO-HÍBRIDOS | C10: MODERADO | D10: HÍBRIDOS | E10: 0.08
B11: =C11&"-"&D11 -> MODERADO-FOFS | C11: MODERADO | D11: FOFS | E11: 0.1
B12: =C12&"-"&D12 -> MODERADO-DESENVOLVIMENTO | C12: MODERADO | D12: DESENVOLVIMENTO | E12: 0.05
B13: =C13&"-"&D13 -> MODERADO-HOTELARIAS | C13: MODERADO | D13: HOTELARIAS | E13: 0.05
... B19: =C19&"-"&D19 -> AGRESSIVO-HOTELARIAS | C19: AGRESSIVO | D19: HOTELARIAS | E19: 0.1
